corrfeatred/__init__.py
corrfeatred/reduce.py
corrfeatred-0.0.3.3.dist-info/LICENSE
corrfeatred-0.0.3.3.dist-info/METADATA
corrfeatred-0.0.3.3.dist-info/WHEEL
corrfeatred-0.0.3.3.dist-info/top_level.txt
corrfeatred-0.0.3.3.dist-info/RECORD
